octopy_energy/__init__.py
octopy_energy/graphql.py
octopy_energy/py.typed
octopy_energy/rest.py
octopy_energy/__test__/__init__.py
octopy_energy/__test__/test_consumption.py
octopy_energy/__test__/test_groupings.py
octopy_energy/tools/__init__.py
octopy_energy/tools/electricity_consumption_and_tariff.py
octopy_energy/tools/electricity_reading.py
octopy_energy/tools/electricity_tariff.py
octopy_energy-1.0.1.dist-info/0BSD.txt
octopy_energy-1.0.1.dist-info/AUTHORS
octopy_energy-1.0.1.dist-info/Apache-2.0.txt
octopy_energy-1.0.1.dist-info/LICENSE
octopy_energy-1.0.1.dist-info/METADATA
octopy_energy-1.0.1.dist-info/MIT.txt
octopy_energy-1.0.1.dist-info/WHEEL
octopy_energy-1.0.1.dist-info/top_level.txt
octopy_energy-1.0.1.dist-info/RECORD
